pylog/__init__.py
pylog/manager.py
pylog/appenders/base.py
pylog/appenders/buffering.py
pylog/appenders/console.py
pylog/appenders/failover.py
pylog/appenders/http_appender.py
pylog/appenders/kafka_appender.py
pylog/appenders/rolling_file.py
pylog/appenders/socket_appender.py
pylog/core/async_queue.py
pylog/core/context.py
pylog/core/log_event.py
pylog/core/logger.py
pylog/core/marker.py
pylog/core/metrics.py
pylog/formatters/base.py
pylog/formatters/json_formatter.py
pylog/formatters/pattern_formatter.py
pylog/infra/config_loader.py
pylog/infra/reloader.py
pylog_4j-2.2.2.dist-info/licenses/LICENSE
pylog_4j-2.2.2.dist-info/METADATA
pylog_4j-2.2.2.dist-info/WHEEL
pylog_4j-2.2.2.dist-info/top_level.txt
pylog_4j-2.2.2.dist-info/RECORD
