Metadata-Version: 2.4
Name: pylog-4j
Version: 2.2.2
Summary: A production-ready logging library for Python inspired by Log4j2
Author-email: PyLog Team <pylog@example.com>
License: MIT
Requires-Python: >=3.8
License-File: LICENSE
Requires-Dist: orjson
Requires-Dist: PyYAML
Requires-Dist: watchdog
Provides-Extra: kafka
Requires-Dist: confluent-kafka; extra == "kafka"
Provides-Extra: dev
Requires-Dist: pytest; extra == "dev"
Requires-Dist: pytest-asyncio; extra == "dev"
Dynamic: license-file
